genfact/__init__.py
genfact/util.py
genfact/data/encoded_fbdata.csv
genfact-1.4.dist-info/LICENSE
genfact-1.4.dist-info/METADATA
genfact-1.4.dist-info/WHEEL
genfact-1.4.dist-info/top_level.txt
genfact-1.4.dist-info/RECORD
