Metadata-Version: 2.1
Name: genfact
Version: 1.4
Summary: A model agnostic and gradient-free optimization method for generating counterfactuals
Home-page: https://github.com/swarna-kpaul/genfact
Author: Swarna Kamal Paul
Author-email: swarna.kpaul@gmail.com
License: UNKNOWN
Project-URL: Bug Tracker, https://github.com/swarna-kpaul/genfact/issues
Keywords: counterfactual,genetic algorithm,genfact
Platform: UNKNOWN
Classifier: Programming Language :: Python :: 3
Classifier: License :: OSI Approved :: MIT License
Classifier: Operating System :: OS Independent
Requires-Python: >=3.6
License-File: LICENSE
Requires-Dist: sklearn
Requires-Dist: pandas
Requires-Dist: scipy
Requires-Dist: numpy
